{
	"song": {
		"player1": "melstyleBF-beach",
		"gfVersion": "melstyleGF-beach",
		"notes": [
			{
				"sectionBeats": 4,
				"sectionNotes": [
					[
						214.285714285714,
						3,
						0
					],
					[
						321.428571428571,
						3,
						0
					],
					[
						428.571428571429,
						2,
						0
					],
					[
						642.857142857143,
						1,
						0
					],
					[
						750,
						0,
						0
					],
					[
						1285.71428571429,
						0,
						0
					],
					[
						1392.85714285714,
						3,
						0
					],
					[
						1500,
						3,
						0
					],
					[
						0,
						0,
						107.142857142857
					],
					[
						857.142857142857,
						2,
						107.142857142857
					],
					[
						1071.42857142857,
						3,
						107.142857142857
					]
				],
				"typeOfSection": 0,
				"gfSection": false,
				"altAnim": false,
				"mustHitSection": false,
				"changeBPM": false,
				"bpm": 150
			},
			{
				"sectionBeats": 4,
				"sectionNotes": [
					[
						1928.57142857143,
						0,
						0
					],
					[
						2035.71428571429,
						0,
						0
					],
					[
						2357.14285714286,
						3,
						0
					],
					[
						2464.28571428571,
						2,
						0
					],
					[
						3000,
						1,
						0
					],
					[
						3107.14285714286,
						3,
						0
					],
					[
						1714.28571428571,
						1,
						107.142857142857
					],
					[
						2142.85714285714,
						1,
						107.142857142857
					],
					[
						2571.42857142857,
						1,
						107.142857142857
					],
					[
						2785.71428571429,
						0,
						107.142857142857
					],
					[
						3214.28571428571,
						1,
						107.142857142857
					]
				],
				"typeOfSection": 0,
				"gfSection": false,
				"altAnim": false,
				"mustHitSection": false,
				"changeBPM": false,
				"bpm": 150
			},
			{
				"sectionBeats": 4,
				"sectionNotes": [
					[
						3642.85714285714,
						1,
						0
					],
					[
						3750,
						1,
						0
					],
					[
						4071.42857142857,
						2,
						0
					],
					[
						4178.57142857143,
						1,
						0
					],
					[
						4714.28571428571,
						2,
						0
					],
					[
						4821.42857142857,
						1,
						0
					],
					[
						3428.57142857143,
						2,
						160.714285714286
					],
					[
						3857.14285714286,
						0,
						107.142857142857
					],
					[
						4285.71428571429,
						0,
						107.142857142857
					],
					[
						4500,
						1,
						107.142857142857
					],
					[
						4928.57142857143,
						3,
						107.142857142857
					]
				],
				"typeOfSection": 0,
				"gfSection": false,
				"altAnim": false,
				"mustHitSection": false,
				"changeBPM": false,
				"bpm": 140
			},
			{
				"sectionBeats": 4,
				"sectionNotes": [
					[
						5357.14285714286,
						0,
						0
					],
					[
						5464.28571428571,
						0,
						0
					],
					[
						5785.71428571429,
						3,
						0
					],
					[
						5892.85714285714,
						2,
						0
					],
					[
						6428.57142857143,
						1,
						0
					],
					[
						6535.71428571429,
						3,
						0
					],
					[
						5142.85714285714,
						1,
						107.142857142857
					],
					[
						5571.42857142857,
						1,
						107.142857142857
					],
					[
						6000,
						1,
						107.142857142857
					],
					[
						6214.28571428571,
						0,
						107.142857142857
					],
					[
						6642.85714285714,
						1,
						107.142857142857
					]
				],
				"typeOfSection": 0,
				"gfSection": false,
				"altAnim": false,
				"mustHitSection": false,
				"changeBPM": false,
				"bpm": 130
			},
			{
				"sectionBeats": 4,
				"sectionNotes": [
					[
						7071.42857142857,
						3,
						0
					],
					[
						7178.57142857143,
						3,
						0
					],
					[
						7285.71428571429,
						2,
						0
					],
					[
						7500,
						1,
						0
					],
					[
						7607.14285714286,
						0,
						0
					],
					[
						8142.85714285714,
						0,
						0
					],
					[
						8250,
						3,
						0
					],
					[
						8357.14285714286,
						3,
						0
					],
					[
						6857.14285714286,
						0,
						107.142857142857
					],
					[
						7714.28571428571,
						2,
						107.142857142857
					],
					[
						7928.57142857143,
						3,
						107.142857142857
					]
				],
				"typeOfSection": 0,
				"gfSection": false,
				"altAnim": false,
				"mustHitSection": true,
				"changeBPM": false,
				"bpm": 130
			},
			{
				"sectionBeats": 4,
				"sectionNotes": [
					[
						8785.71428571429,
						0,
						0
					],
					[
						8892.85714285714,
						0,
						0
					],
					[
						9214.28571428571,
						3,
						0
					],
					[
						9321.42857142857,
						2,
						0
					],
					[
						9857.14285714286,
						1,
						0
					],
					[
						9964.28571428571,
						3,
						0
					],
					[
						8571.42857142857,
						1,
						107.142857142857
					],
					[
						9000,
						1,
						107.142857142857
					],
					[
						9428.57142857143,
						1,
						107.142857142857
					],
					[
						9642.85714285714,
						0,
						107.142857142857
					],
					[
						10071.4285714286,
						1,
						107.142857142857
					]
				],
				"typeOfSection": 0,
				"gfSection": false,
				"altAnim": false,
				"mustHitSection": true,
				"changeBPM": false,
				"bpm": 130
			},
			{
				"sectionBeats": 4,
				"sectionNotes": [
					[
						10500,
						1,
						0
					],
					[
						10607.1428571429,
						1,
						0
					],
					[
						10928.5714285714,
						2,
						0
					],
					[
						11035.7142857143,
						1,
						0
					],
					[
						11571.4285714286,
						2,
						0
					],
					[
						11678.5714285714,
						1,
						0
					],
					[
						10285.7142857143,
						2,
						160.714285714286
					],
					[
						10714.2857142857,
						0,
						107.142857142857
					],
					[
						11142.8571428571,
						0,
						107.142857142857
					],
					[
						11357.1428571429,
						1,
						107.142857142857
					],
					[
						11785.7142857143,
						3,
						107.142857142857
					]
				],
				"typeOfSection": 0,
				"gfSection": false,
				"altAnim": false,
				"mustHitSection": true,
				"changeBPM": false,
				"bpm": 130
			},
			{
				"sectionBeats": 4,
				"sectionNotes": [
					[
						12214.2857142857,
						0,
						0
					],
					[
						12321.4285714286,
						0,
						0
					],
					[
						12642.8571428571,
						3,
						0
					],
					[
						12750,
						2,
						0
					],
					[
						13285.7142857143,
						1,
						0
					],
					[
						13392.8571428571,
						3,
						0
					],
					[
						12000,
						1,
						107.142857142857
					],
					[
						12428.5714285714,
						1,
						107.142857142857
					],
					[
						12857.1428571429,
						1,
						107.142857142857
					],
					[
						13071.4285714286,
						0,
						107.142857142857
					],
					[
						13500,
						1,
						107.142857142857
					]
				],
				"typeOfSection": 0,
				"gfSection": false,
				"altAnim": false,
				"mustHitSection": true,
				"changeBPM": false,
				"bpm": 130
			},
			{
				"sectionBeats": 4,
				"sectionNotes": [
					[
						13714.2857142857,
						0,
						107.142857142857
					],
					[
						13928.5714285714,
						3,
						0
					],
					[
						14035.7142857143,
						2,
						0
					],
					[
						14142.8571428571,
						1,
						0
					],
					[
						14250,
						2,
						0
					],
					[
						14357.1428571429,
						1,
						0
					],
					[
						14464.2857142857,
						0,
						0
					],
					[
						14571.4285714286,
						3,
						0
					],
					[
						14785.7142857143,
						2,
						0
					],
					[
						14892.8571428571,
						0,
						0
					],
					[
						15000,
						3,
						0
					],
					[
						15214.2857142857,
						2,
						0
					],
					[
						15321.4285714286,
						0,
						0
					]
				],
				"typeOfSection": 0,
				"gfSection": false,
				"altAnim": false,
				"mustHitSection": false,
				"changeBPM": false,
				"bpm": 130
			},
			{
				"sectionBeats": 4,
				"sectionNotes": [
					[
						15428.5714285714,
						0,
						107.142857142857
					],
					[
						15642.8571428571,
						1,
						0
					],
					[
						15750,
						2,
						0
					],
					[
						15857.1428571429,
						3,
						107.142857142857
					],
					[
						16071.4285714286,
						1,
						107.142857142857
					],
					[
						16285.7142857143,
						3,
						107.142857142857
					],
					[
						16285.7142857143,
						2,
						0
					],
					[
						16500,
						2,
						107.142857142857
					],
					[
						16714.2857142857,
						1,
						107.142857142857
					],
					[
						16928.5714285714,
						0,
						107.142857142857
					]
				],
				"typeOfSection": 0,
				"gfSection": false,
				"altAnim": false,
				"mustHitSection": false,
				"changeBPM": false,
				"bpm": 130
			},
			{
				"sectionBeats": 4,
				"sectionNotes": [
					[
						17142.8571428571,
						3,
						107.142857142857
					],
					[
						17357.1428571429,
						1,
						0
					],
					[
						17464.2857142857,
						3,
						107.142857142857
					],
					[
						17678.5714285714,
						2,
						0
					],
					[
						17785.7142857143,
						1,
						107.142857142857
					],
					[
						18000,
						2,
						0
					],
					[
						18107.1428571429,
						0,
						0
					],
					[
						18214.2857142857,
						2,
						0
					],
					[
						18321.4285714286,
						3,
						0
					],
					[
						18428.5714285714,
						1,
						107.142857142857
					],
					[
						18642.8571428571,
						2,
						107.142857142857
					]
				],
				"typeOfSection": 0,
				"gfSection": false,
				"altAnim": false,
				"mustHitSection": false,
				"changeBPM": false,
				"bpm": 130
			},
			{
				"sectionBeats": 4,
				"sectionNotes": [
					[
						18857.1428571429,
						1,
						107.142857142857
					],
					[
						19178.5714285714,
						0,
						107.142857142857
					],
					[
						19500,
						2,
						0
					],
					[
						19607.1428571429,
						0,
						0
					],
					[
						19714.2857142857,
						1,
						321.428571428571
					],
					[
						20142.8571428571,
						3,
						321.428571428571
					]
				],
				"typeOfSection": 0,
				"gfSection": false,
				"altAnim": false,
				"mustHitSection": false,
				"changeBPM": false,
				"bpm": 130
			},
			{
				"sectionBeats": 4,
				"sectionNotes": [
					[
						20571.4285714286,
						0,
						107.142857142857
					],
					[
						20785.7142857143,
						3,
						0
					],
					[
						20892.8571428571,
						2,
						0
					],
					[
						21000,
						1,
						0
					],
					[
						21107.1428571429,
						2,
						0
					],
					[
						21214.2857142857,
						1,
						0
					],
					[
						21321.4285714286,
						0,
						0
					],
					[
						21428.5714285714,
						3,
						0
					],
					[
						21642.8571428571,
						2,
						0
					],
					[
						21750,
						0,
						0
					],
					[
						21857.1428571429,
						3,
						0
					],
					[
						22071.4285714286,
						2,
						0
					],
					[
						22178.5714285714,
						0,
						0
					],
					[
						20571.4285714286,
						6,
						750
					],
					[
						21857.1428571429,
						7,
						321.428571428571
					]
				],
				"typeOfSection": 0,
				"gfSection": false,
				"altAnim": false,
				"mustHitSection": true,
				"changeBPM": false,
				"bpm": 130
			},
			{
				"sectionBeats": 4,
				"sectionNotes": [
					[
						22285.7142857143,
						0,
						107.142857142857
					],
					[
						22500,
						1,
						0
					],
					[
						22607.1428571429,
						2,
						0
					],
					[
						22714.2857142857,
						3,
						107.142857142857
					],
					[
						22928.5714285714,
						1,
						107.142857142857
					],
					[
						23142.8571428571,
						3,
						107.142857142857
					],
					[
						23142.8571428571,
						2,
						0
					],
					[
						23357.1428571429,
						2,
						107.142857142857
					],
					[
						23571.4285714286,
						1,
						107.142857142857
					],
					[
						23785.7142857143,
						0,
						107.142857142857
					],
					[
						22285.7142857143,
						5,
						428.571428571428
					],
					[
						23142.8571428571,
						6,
						321.428571428571
					],
					[
						23571.4285714286,
						5,
						107.142857142857
					],
					[
						23785.7142857143,
						7,
						107.142857142857
					]
				],
				"typeOfSection": 0,
				"gfSection": false,
				"altAnim": false,
				"mustHitSection": true,
				"changeBPM": false,
				"bpm": 130
			},
			{
				"sectionBeats": 4,
				"sectionNotes": [
					[
						24000,
						3,
						107.142857142857
					],
					[
						24214.2857142857,
						1,
						0
					],
					[
						24321.4285714286,
						3,
						107.142857142857
					],
					[
						24535.7142857143,
						2,
						0
					],
					[
						24642.8571428571,
						1,
						107.142857142857
					],
					[
						24857.1428571429,
						2,
						0
					],
					[
						24964.2857142857,
						0,
						0
					],
					[
						25071.4285714286,
						2,
						0
					],
					[
						25178.5714285714,
						3,
						0
					],
					[
						25285.7142857143,
						1,
						107.142857142857
					],
					[
						25500,
						2,
						107.142857142857
					],
					[
						24000,
						6,
						428.571428571428
					],
					[
						24857.1428571429,
						7,
						321.428571428571
					],
					[
						25285.7142857143,
						4,
						321.428571428571
					]
				],
				"typeOfSection": 0,
				"gfSection": false,
				"altAnim": false,
				"mustHitSection": true,
				"changeBPM": false,
				"bpm": 130
			},
			{
				"sectionBeats": 4,
				"sectionNotes": [
					[
						25714.2857142857,
						1,
						107.142857142857
					],
					[
						26035.7142857143,
						0,
						107.142857142857
					],
					[
						26357.1428571429,
						2,
						0
					],
					[
						26464.2857142857,
						0,
						0
					],
					[
						26571.4285714286,
						1,
						321.428571428571
					],
					[
						27000,
						3,
						321.428571428571
					],
					[
						25714.2857142857,
						7,
						321.428571428571
					],
					[
						26142.8571428571,
						5,
						321.428571428571
					],
					[
						26571.4285714286,
						6,
						321.428571428571
					],
					[
						27000,
						4,
						321.428571428571
					]
				],
				"typeOfSection": 0,
				"gfSection": false,
				"altAnim": false,
				"mustHitSection": true,
				"changeBPM": false,
				"bpm": 130
			},
			{
				"sectionBeats": 4,
				"sectionNotes": [
					[
						27428.5714285714,
						0,
						107.142857142857
					],
					[
						27642.8571428571,
						3,
						0
					],
					[
						27750,
						2,
						0
					],
					[
						27857.1428571429,
						0,
						0
					],
					[
						27910.7142857143,
						2,
						0
					],
					[
						27964.2857142857,
						1,
						0
					],
					[
						28178.5714285714,
						1,
						0
					],
					[
						28071.4285714286,
						3,
						0
					],
					[
						28285.7142857143,
						0,
						0
					],
					[
						28392.8571428571,
						2,
						0
					],
					[
						28500,
						1,
						0
					],
					[
						28607.1428571429,
						3,
						0
					],
					[
						28714.2857142857,
						1,
						0
					],
					[
						28821.4285714286,
						0,
						0
					],
					[
						28928.5714285714,
						3,
						0
					],
					[
						29035.7142857143,
						1,
						0
					]
				],
				"typeOfSection": 0,
				"gfSection": false,
				"altAnim": false,
				"mustHitSection": false,
				"changeBPM": false,
				"bpm": 130
			},
			{
				"sectionBeats": 4,
				"sectionNotes": [
					[
						29142.8571428571,
						2,
						0
					],
					[
						29357.1428571429,
						0,
						0
					],
					[
						29464.2857142857,
						1,
						0
					],
					[
						29678.5714285714,
						0,
						0
					],
					[
						29785.7142857143,
						3,
						0
					],
					[
						29892.8571428571,
						2,
						0
					],
					[
						30000,
						3,
						0
					],
					[
						30214.2857142857,
						1,
						0
					],
					[
						30321.4285714286,
						3,
						0
					],
					[
						30535.7142857143,
						1,
						214.285714285714
					]
				],
				"typeOfSection": 0,
				"gfSection": false,
				"altAnim": false,
				"mustHitSection": false,
				"changeBPM": false,
				"bpm": 130
			},
			{
				"sectionBeats": 4,
				"sectionNotes": [
					[
						30857.1428571429,
						2,
						214.285714285714
					],
					[
						31392.8571428571,
						1,
						0
					],
					[
						31285.7142857143,
						3,
						0
					],
					[
						31500,
						2,
						107.142857142857
					],
					[
						31714.2857142857,
						1,
						214.285714285714
					],
					[
						32142.8571428571,
						0,
						107.142857142857
					],
					[
						32357.1428571429,
						2,
						107.142857142857
					],
					[
						32035.7142857143,
						2,
						0
					],
					[
						31285.7142857143,
						7,
						107.142857142857,
						"GF Sing"
					],
					[
						30857.1428571429,
						3,
						216,
						"brandy"
					],
					[
						31285.7142857143,
						0,
						108,
						"brandy"
					],
					[
						31500,
						3,
						108,
						"brandy"
					],
					[
						31714.2857142857,
						2,
						324,
						"brandy"
					],
					[
						32142.8571428571,
						1,
						324,
						"brandy"
					]
				],
				"typeOfSection": 0,
				"gfSection": false,
				"altAnim": false,
				"mustHitSection": false,
				"changeBPM": false,
				"bpm": 130
			},
			{
				"sectionBeats": 4,
				"sectionNotes": [
					[
						32571.4285714286,
						0,
						214.285714285714
					],
					[
						32892.8571428571,
						1,
						214.285714285714
					],
					[
						33214.2857142857,
						2,
						107.142857142857
					],
					[
						33857.1428571428,
						1,
						0
					],
					[
						34071.4285714286,
						0,
						0
					],
					[
						33428.5714285714,
						3,
						267.857142857143
					],
					[
						32571.4285714286,
						3,
						324,
						"brandy"
					],
					[
						33214.2857142857,
						1,
						108,
						"brandy"
					],
					[
						33428.5714285714,
						0,
						0,
						"brandy"
					],
					[
						33428.5714285714,
						2,
						324,
						"brandy"
					],
					[
						33857.1428571428,
						2,
						0,
						"brandy"
					]
				],
				"typeOfSection": 0,
				"gfSection": false,
				"altAnim": false,
				"mustHitSection": false,
				"changeBPM": false,
				"bpm": 130
			},
			{
				"sectionBeats": 4,
				"sectionNotes": [
					[
						34285.7142857143,
						0,
						107.142857142857
					],
					[
						34500,
						3,
						0
					],
					[
						34607.1428571429,
						2,
						0
					],
					[
						34714.2857142857,
						0,
						0
					],
					[
						34767.8571428571,
						2,
						0
					],
					[
						34821.4285714286,
						1,
						0
					],
					[
						35035.7142857143,
						1,
						0
					],
					[
						34928.5714285714,
						3,
						0
					],
					[
						35357.1428571429,
						1,
						0
					],
					[
						35464.2857142857,
						3,
						0
					],
					[
						35571.4285714286,
						1,
						0
					],
					[
						35678.5714285714,
						0,
						0
					],
					[
						35785.7142857143,
						3,
						0
					],
					[
						35892.8571428571,
						1,
						0
					],
					[
						35142.8571428571,
						0,
						0
					],
					[
						35250,
						2,
						0
					]
				],
				"typeOfSection": 0,
				"gfSection": false,
				"altAnim": false,
				"mustHitSection": true,
				"changeBPM": false,
				"bpm": 130
			},
			{
				"sectionBeats": 4,
				"sectionNotes": [
					[
						36000,
						2,
						0
					],
					[
						36214.2857142857,
						0,
						0
					],
					[
						36321.4285714286,
						1,
						0
					],
					[
						36535.7142857143,
						0,
						0
					],
					[
						36642.8571428571,
						3,
						0
					],
					[
						36750,
						2,
						0
					],
					[
						36857.1428571429,
						3,
						0
					],
					[
						37071.4285714286,
						1,
						0
					],
					[
						37178.5714285714,
						3,
						0
					],
					[
						37392.8571428571,
						1,
						214.285714285714
					]
				],
				"typeOfSection": 0,
				"gfSection": false,
				"altAnim": false,
				"mustHitSection": true,
				"changeBPM": false,
				"bpm": 130
			},
			{
				"sectionBeats": 4,
				"sectionNotes": [
					[
						37714.2857142857,
						2,
						214.285714285714
					],
					[
						38250,
						1,
						0
					],
					[
						38142.8571428571,
						3,
						0
					],
					[
						38357.1428571428,
						2,
						107.142857142857
					],
					[
						38571.4285714286,
						1,
						214.285714285714
					],
					[
						39000,
						0,
						107.142857142857
					],
					[
						39214.2857142857,
						2,
						107.142857142857
					],
					[
						38892.8571428571,
						2,
						0
					],
					[
						37714.2857142857,
						6,
						214.285714285714
					],
					[
						38142.8571428571,
						7,
						107.142857142857
					],
					[
						38357.1428571429,
						6,
						107.142857142857
					],
					[
						38571.4285714286,
						7,
						321.428571428571
					],
					[
						39000,
						5,
						321.428571428571
					]
				],
				"typeOfSection": 0,
				"gfSection": false,
				"altAnim": false,
				"mustHitSection": true,
				"changeBPM": false,
				"bpm": 130
			},
			{
				"sectionBeats": 4,
				"sectionNotes": [
					[
						39428.5714285714,
						0,
						214.285714285714
					],
					[
						39750,
						1,
						214.285714285714
					],
					[
						40071.4285714286,
						2,
						107.142857142857
					],
					[
						40714.2857142857,
						1,
						0
					],
					[
						40928.5714285714,
						0,
						0
					],
					[
						40285.7142857143,
						3,
						267.857142857143
					],
					[
						40285.7142857143,
						5,
						0
					],
					[
						40071.4285714286,
						6,
						107.142857142857
					],
					[
						39428.5714285714,
						4,
						321.428571428571
					],
					[
						40714.2857142857,
						6,
						321.428571428571
					],
					[
						40285.7142857143,
						7,
						321.428571428571
					]
				],
				"typeOfSection": 0,
				"gfSection": false,
				"altAnim": false,
				"mustHitSection": true,
				"changeBPM": false,
				"bpm": 130
			},
			{
				"sectionBeats": 4,
				"sectionNotes": [
					[
						41142.8571428572,
						2,
						0,
						"brandy"
					],
					[
						41250,
						0,
						0,
						"brandy"
					],
					[
						41357.1428571429,
						1,
						0,
						"brandy"
					],
					[
						41464.2857142857,
						3,
						0,
						"brandy"
					],
					[
						41571.4285714286,
						0,
						0,
						"brandy"
					],
					[
						41785.7142857143,
						1,
						0,
						"brandy"
					],
					[
						41892.8571428572,
						2,
						0,
						"brandy"
					],
					[
						42000,
						1,
						0,
						"brandy"
					],
					[
						42053.5714285714,
						0,
						0,
						"brandy"
					],
					[
						42107.1428571429,
						1,
						0,
						"brandy"
					],
					[
						42160.7142857143,
						3,
						0,
						"brandy"
					],
					[
						42214.2857142857,
						0,
						0,
						"brandy"
					],
					[
						42321.4285714286,
						3,
						0,
						"brandy"
					],
					[
						42428.5714285714,
						2,
						0,
						"brandy"
					],
					[
						42535.7142857143,
						1,
						0,
						"brandy"
					],
					[
						42750,
						0,
						0,
						"brandy"
					]
				],
				"typeOfSection": 0,
				"gfSection": false,
				"altAnim": false,
				"mustHitSection": false,
				"changeBPM": false,
				"bpm": 130
			},
			{
				"sectionBeats": 4,
				"sectionNotes": [
					[
						42857.1428571429,
						1,
						0,
						"brandy"
					],
					[
						43071.4285714286,
						1,
						0,
						"brandy"
					],
					[
						43178.5714285714,
						3,
						0,
						"brandy"
					],
					[
						43285.7142857143,
						1,
						0,
						"brandy"
					],
					[
						43392.8571428572,
						3,
						0,
						"brandy"
					],
					[
						43607.1428571429,
						1,
						0,
						"brandy"
					],
					[
						43714.2857142857,
						0,
						324,
						"brandy"
					],
					[
						44142.8571428572,
						1,
						324,
						"brandy"
					]
				],
				"typeOfSection": 0,
				"gfSection": false,
				"altAnim": false,
				"mustHitSection": false,
				"changeBPM": false,
				"bpm": 130
			},
			{
				"sectionBeats": 4,
				"sectionNotes": [
					[
						44571.4285714286,
						3,
						0,
						"brandy"
					],
					[
						44678.5714285714,
						2,
						0,
						"brandy"
					],
					[
						44785.7142857143,
						0,
						0,
						"brandy"
					],
					[
						44892.8571428572,
						1,
						0,
						"brandy"
					],
					[
						45000,
						3,
						0,
						"brandy"
					],
					[
						45107.1428571429,
						0,
						0,
						"brandy"
					],
					[
						45214.2857142857,
						3,
						0,
						"brandy"
					],
					[
						45321.4285714286,
						2,
						0,
						"brandy"
					],
					[
						45642.8571428572,
						2,
						0,
						"brandy"
					],
					[
						45750,
						0,
						0,
						"brandy"
					],
					[
						45857.1428571429,
						3,
						0,
						"brandy"
					],
					[
						45964.2857142857,
						3,
						0,
						"brandy"
					],
					[
						46071.4285714286,
						1,
						0,
						"brandy"
					],
					[
						45428.5714285714,
						1,
						108,
						"brandy"
					],
					[
						46178.5714285714,
						2,
						0,
						"brandy"
					]
				],
				"typeOfSection": 0,
				"gfSection": false,
				"altAnim": false,
				"mustHitSection": false,
				"changeBPM": false,
				"bpm": 130
			},
			{
				"sectionBeats": 4,
				"sectionNotes": [
					[
						46285.7142857143,
						0,
						0,
						"brandy"
					],
					[
						46500,
						2,
						0,
						"brandy"
					],
					[
						46607.1428571429,
						3,
						0,
						"brandy"
					],
					[
						46714.2857142857,
						2,
						0,
						"brandy"
					],
					[
						46928.5714285714,
						0,
						0,
						"brandy"
					],
					[
						47142.8571428572,
						2,
						0,
						"brandy"
					],
					[
						47357.1428571429,
						2,
						0,
						"brandy"
					],
					[
						47464.2857142857,
						2,
						0,
						"brandy"
					],
					[
						47571.4285714286,
						1,
						0,
						"brandy"
					],
					[
						47678.5714285714,
						0,
						0,
						"brandy"
					],
					[
						47785.7142857143,
						2,
						0,
						"brandy"
					],
					[
						47892.8571428572,
						3,
						0,
						"brandy"
					]
				],
				"typeOfSection": 0,
				"gfSection": false,
				"altAnim": false,
				"mustHitSection": false,
				"changeBPM": false,
				"bpm": 130
			},
			{
				"sectionBeats": 4,
				"sectionNotes": [
					[
						48000,
						2,
						0
					],
					[
						48107.1428571429,
						0,
						0
					],
					[
						48214.2857142857,
						1,
						0
					],
					[
						48321.4285714286,
						3,
						0
					],
					[
						48428.5714285714,
						0,
						0
					],
					[
						48642.8571428572,
						1,
						0
					],
					[
						48750,
						2,
						0
					],
					[
						48857.1428571429,
						1,
						0
					],
					[
						48910.7142857143,
						0,
						0
					],
					[
						48964.2857142857,
						1,
						0
					],
					[
						49017.8571428572,
						3,
						0
					],
					[
						49071.4285714286,
						0,
						0
					],
					[
						49178.5714285714,
						3,
						0
					],
					[
						49285.7142857143,
						2,
						0
					],
					[
						49392.8571428572,
						1,
						0
					],
					[
						49607.1428571429,
						0,
						0
					],
					[
						48000,
						7,
						324,
						"brandy"
					]
				],
				"typeOfSection": 0,
				"gfSection": false,
				"altAnim": false,
				"mustHitSection": true,
				"changeBPM": false,
				"bpm": 130
			},
			{
				"sectionBeats": 4,
				"sectionNotes": [
					[
						49714.2857142857,
						1,
						0
					],
					[
						49928.5714285715,
						1,
						0
					],
					[
						50035.7142857143,
						3,
						0
					],
					[
						50142.8571428572,
						1,
						0
					],
					[
						50250,
						3,
						0
					],
					[
						50464.2857142857,
						1,
						0
					],
					[
						50571.4285714286,
						0,
						321.428571428571
					],
					[
						51000,
						1,
						321.428571428571
					]
				],
				"typeOfSection": 0,
				"gfSection": false,
				"altAnim": false,
				"mustHitSection": true,
				"changeBPM": false,
				"bpm": 130
			},
			{
				"sectionBeats": 4,
				"sectionNotes": [
					[
						51428.5714285714,
						3,
						0
					],
					[
						51535.7142857143,
						2,
						0
					],
					[
						51642.8571428572,
						0,
						0
					],
					[
						51750,
						1,
						0
					],
					[
						51857.1428571429,
						3,
						0
					],
					[
						51964.2857142857,
						0,
						0
					],
					[
						52071.4285714286,
						3,
						0
					],
					[
						52178.5714285714,
						2,
						0
					],
					[
						52285.7142857143,
						1,
						107.142857142857
					],
					[
						52500,
						2,
						0
					],
					[
						52607.1428571429,
						0,
						0
					],
					[
						52714.2857142857,
						3,
						0
					],
					[
						52821.4285714286,
						3,
						0
					],
					[
						52928.5714285714,
						1,
						0
					],
					[
						53035.7142857143,
						2,
						0
					],
					[
						51428.5714285715,
						6,
						324,
						"brandy"
					],
					[
						52178.5714285715,
						7,
						325,
						"brandy"
					],
					[
						52714.2857142857,
						7,
						0,
						"brandy"
					],
					[
						52821.4285714286,
						7,
						0,
						"brandy"
					],
					[
						52928.5714285715,
						5,
						0,
						"brandy"
					],
					[
						53035.7142857143,
						6,
						0,
						"brandy"
					]
				],
				"typeOfSection": 0,
				"gfSection": false,
				"altAnim": false,
				"mustHitSection": true,
				"changeBPM": false,
				"bpm": 130
			},
			{
				"sectionBeats": 4,
				"sectionNotes": [
					[
						53142.8571428572,
						0,
						0
					],
					[
						53357.1428571429,
						2,
						0
					],
					[
						53571.4285714286,
						2,
						0
					],
					[
						53785.7142857143,
						0,
						0
					],
					[
						54000,
						2,
						0
					],
					[
						53464.2857142857,
						3,
						0
					],
					[
						54214.2857142857,
						2,
						0
					],
					[
						54321.4285714286,
						2,
						0
					],
					[
						54428.5714285714,
						1,
						0
					],
					[
						54535.7142857143,
						0,
						0
					],
					[
						54642.8571428572,
						2,
						0
					],
					[
						54750,
						3,
						0
					],
					[
						53142.8571428572,
						6,
						540,
						"brandy"
					],
					[
						53571.4285714286,
						4,
						540,
						"brandy"
					],
					[
						54000,
						5,
						756,
						"brandy"
					]
				],
				"typeOfSection": 0,
				"gfSection": false,
				"altAnim": false,
				"mustHitSection": true,
				"changeBPM": false,
				"bpm": 130
			},
			{
				"sectionBeats": 4,
				"sectionNotes": [
					[
						54857.1428571429,
						5,
						321.428571428571
					],
					[
						55285.7142857143,
						1,
						0,
						"brandy"
					],
					[
						55392.8571428572,
						1,
						0,
						"brandy"
					],
					[
						55500,
						0,
						324,
						"brandy"
					],
					[
						54857.1428571429,
						2,
						324,
						"brandy"
					],
					[
						56142.8571428572,
						1,
						324,
						"brandy"
					]
				],
				"typeOfSection": 0,
				"gfSection": false,
				"altAnim": false,
				"mustHitSection": false,
				"changeBPM": false,
				"bpm": 130
			},
			{
				"sectionBeats": 4,
				"sectionNotes": [
					[
						56571.4285714286,
						3,
						324,
						"brandy"
					],
					[
						57000,
						1,
						108,
						"brandy"
					],
					[
						57214.2857142858,
						3,
						0,
						"brandy"
					],
					[
						57321.4285714286,
						0,
						0,
						"brandy"
					],
					[
						57428.5714285715,
						1,
						0,
						"brandy"
					],
					[
						57428.5714285715,
						3,
						324,
						"brandy"
					],
					[
						57857.1428571429,
						1,
						324,
						"brandy"
					]
				],
				"typeOfSection": 0,
				"gfSection": false,
				"altAnim": false,
				"mustHitSection": false,
				"changeBPM": false,
				"bpm": 130
			},
			{
				"sectionBeats": 4,
				"sectionNotes": [
					[
						58285.7142857143,
						2,
						324,
						"brandy"
					],
					[
						58714.2857142858,
						0,
						108,
						"brandy"
					],
					[
						58928.5714285715,
						1,
						108,
						"brandy"
					],
					[
						59142.8571428572,
						2,
						324,
						"brandy"
					],
					[
						59571.4285714286,
						1,
						324,
						"brandy"
					]
				],
				"typeOfSection": 0,
				"gfSection": false,
				"altAnim": false,
				"mustHitSection": false,
				"changeBPM": false,
				"bpm": 130
			},
			{
				"sectionBeats": 4,
				"sectionNotes": [
					[
						60000,
						3,
						0,
						"brandy"
					],
					[
						60107.1428571429,
						3,
						0,
						"brandy"
					],
					[
						60428.5714285715,
						1,
						0,
						"brandy"
					],
					[
						60321.4285714286,
						2,
						0,
						"brandy"
					],
					[
						60214.2857142858,
						1,
						0,
						"brandy"
					],
					[
						60535.7142857143,
						1,
						0,
						"brandy"
					],
					[
						60642.8571428572,
						2,
						0,
						"brandy"
					],
					[
						60750,
						1,
						0,
						"brandy"
					],
					[
						60857.1428571429,
						2,
						0,
						"brandy"
					],
					[
						60964.2857142858,
						0,
						0,
						"brandy"
					],
					[
						61178.5714285715,
						2,
						0,
						"brandy"
					],
					[
						61285.7142857143,
						3,
						0,
						"brandy"
					],
					[
						61500,
						1,
						108,
						"brandy"
					]
				],
				"typeOfSection": 0,
				"gfSection": false,
				"altAnim": false,
				"mustHitSection": false,
				"changeBPM": false,
				"bpm": 130
			},
			{
				"sectionBeats": 4,
				"sectionNotes": [
					[
						62142.8571428572,
						1,
						0
					],
					[
						62250,
						1,
						0
					],
					[
						61714.2857142858,
						2,
						321.428571428571
					],
					[
						62357.1428571429,
						0,
						321.428571428571
					],
					[
						63000,
						1,
						321.428571428571
					]
				],
				"typeOfSection": 0,
				"gfSection": false,
				"altAnim": false,
				"mustHitSection": true,
				"changeBPM": false,
				"bpm": 130
			},
			{
				"sectionBeats": 4,
				"sectionNotes": [
					[
						63428.5714285715,
						3,
						321.428571428571
					],
					[
						63857.1428571429,
						1,
						107.142857142857
					],
					[
						64071.4285714286,
						3,
						0
					],
					[
						64178.5714285715,
						0,
						0
					],
					[
						64285.7142857143,
						3,
						321.428571428571
					],
					[
						64285.7142857143,
						1,
						0
					],
					[
						64714.2857142858,
						1,
						321.428571428571
					]
				],
				"typeOfSection": 0,
				"gfSection": false,
				"altAnim": false,
				"mustHitSection": true,
				"changeBPM": false,
				"bpm": 130
			},
			{
				"sectionBeats": 4,
				"sectionNotes": [
					[
						65571.4285714286,
						0,
						107.142857142857
					],
					[
						65785.7142857143,
						1,
						107.142857142857
					],
					[
						65142.8571428572,
						2,
						321.428571428571
					],
					[
						66000.0000000001,
						2,
						321.428571428571
					],
					[
						66428.5714285715,
						1,
						321.428571428571
					]
				],
				"typeOfSection": 0,
				"gfSection": false,
				"altAnim": false,
				"mustHitSection": true,
				"changeBPM": false,
				"bpm": 130
			},
			{
				"sectionBeats": 4,
				"sectionNotes": [
					[
						66857.1428571429,
						3,
						0
					],
					[
						67178.5714285715,
						2,
						0
					],
					[
						67071.4285714286,
						1,
						0
					],
					[
						66964.2857142858,
						3,
						0
					],
					[
						67285.7142857143,
						1,
						0
					],
					[
						67392.8571428572,
						1,
						0
					],
					[
						67500.0000000001,
						2,
						0
					],
					[
						67607.1428571429,
						1,
						0
					],
					[
						67714.2857142858,
						2,
						0
					],
					[
						67821.4285714286,
						0,
						0
					],
					[
						68035.7142857143,
						2,
						0
					],
					[
						68142.8571428572,
						3,
						107.142857142857
					],
					[
						68357.1428571429,
						1,
						107.142857142857
					]
				],
				"typeOfSection": 0,
				"gfSection": false,
				"altAnim": false,
				"mustHitSection": true,
				"changeBPM": false,
				"bpm": 130
			},
			{
				"sectionBeats": 4,
				"sectionNotes": [
					[
						68571.4285714286,
						2,
						0,
						"brandy"
					],
					[
						68678.5714285715,
						1,
						0,
						"brandy"
					],
					[
						68785.7142857143,
						3,
						0,
						"brandy"
					],
					[
						68892.8571428572,
						0,
						0,
						"brandy"
					],
					[
						69000.0000000001,
						2,
						0,
						"brandy"
					],
					[
						69107.1428571429,
						3,
						0,
						"brandy"
					],
					[
						69214.2857142858,
						0,
						0,
						"brandy"
					],
					[
						69321.4285714286,
						1,
						108,
						"brandy"
					],
					[
						69535.7142857143,
						3,
						0,
						"brandy"
					],
					[
						69642.8571428572,
						0,
						0,
						"brandy"
					],
					[
						69750.0000000001,
						3,
						0,
						"brandy"
					],
					[
						69857.1428571429,
						2,
						0,
						"brandy"
					],
					[
						69964.2857142858,
						0,
						0,
						"brandy"
					],
					[
						70071.4285714286,
						3,
						0,
						"brandy"
					],
					[
						70178.5714285715,
						2,
						0,
						"brandy"
					]
				],
				"typeOfSection": 0,
				"gfSection": false,
				"altAnim": false,
				"mustHitSection": false,
				"changeBPM": false,
				"bpm": 130
			},
			{
				"sectionBeats": 4,
				"sectionNotes": [
					[
						70285.7142857143,
						0,
						0,
						"brandy"
					],
					[
						70392.8571428572,
						0,
						0,
						"brandy"
					],
					[
						70500,
						1,
						0,
						"brandy"
					],
					[
						70607.1428571429,
						2,
						0,
						"brandy"
					],
					[
						70714.2857142858,
						3,
						0,
						"brandy"
					],
					[
						70821.4285714286,
						0,
						0,
						"brandy"
					],
					[
						70928.5714285715,
						3,
						0,
						"brandy"
					],
					[
						71035.7142857143,
						2,
						0,
						"brandy"
					],
					[
						71142.8571428572,
						1,
						0,
						"brandy"
					],
					[
						71250,
						2,
						0,
						"brandy"
					],
					[
						71357.1428571429,
						1,
						0,
						"brandy"
					],
					[
						71464.2857142858,
						2,
						0,
						"brandy"
					],
					[
						71571.4285714286,
						3,
						0,
						"brandy"
					],
					[
						71678.5714285715,
						3,
						0,
						"brandy"
					],
					[
						71785.7142857143,
						0,
						0,
						"brandy"
					],
					[
						71892.8571428572,
						2,
						0,
						"brandy"
					]
				],
				"typeOfSection": 0,
				"gfSection": false,
				"altAnim": false,
				"mustHitSection": false,
				"changeBPM": false,
				"bpm": 130
			},
			{
				"sectionBeats": 4,
				"sectionNotes": [
					[
						72000,
						1,
						0,
						"brandy"
					],
					[
						72214.2857142858,
						1,
						0,
						"brandy"
					],
					[
						72321.4285714286,
						2,
						0,
						"brandy"
					],
					[
						72428.5714285715,
						0,
						0,
						"brandy"
					],
					[
						72642.8571428572,
						2,
						0,
						"brandy"
					],
					[
						72857.1428571429,
						3,
						0,
						"brandy"
					],
					[
						72964.2857142858,
						2,
						0,
						"brandy"
					],
					[
						73178.5714285715,
						1,
						0,
						"brandy"
					],
					[
						73607.1428571429,
						1,
						0,
						"brandy"
					]
				],
				"typeOfSection": 0,
				"gfSection": false,
				"altAnim": false,
				"mustHitSection": false,
				"changeBPM": false,
				"bpm": 130
			},
			{
				"sectionBeats": 4,
				"sectionNotes": [
					[
						73714.2857142858,
						2,
						324,
						"brandy"
					],
					[
						74464.2857142858,
						0,
						0,
						"brandy"
					],
					[
						74571.4285714286,
						1,
						324,
						"brandy"
					],
					[
						75000,
						3,
						324,
						"brandy"
					]
				],
				"typeOfSection": 0,
				"gfSection": false,
				"altAnim": false,
				"mustHitSection": false,
				"changeBPM": false,
				"bpm": 125
			},
			{
				"sectionBeats": 4,
				"sectionNotes": [
					[
						75428.5714285714,
						2,
						0
					],
					[
						75535.7142857143,
						1,
						0
					],
					[
						75642.8571428572,
						3,
						0
					],
					[
						75750.0000000001,
						0,
						0
					],
					[
						75857.142857143,
						2,
						0
					],
					[
						75964.2857142858,
						3,
						0
					],
					[
						76071.4285714287,
						0,
						0
					],
					[
						76392.8571428572,
						3,
						0
					],
					[
						76607.142857143,
						3,
						0
					],
					[
						76714.2857142858,
						2,
						0
					],
					[
						76500.0000000001,
						0,
						0
					],
					[
						76821.4285714287,
						0,
						0
					],
					[
						76928.5714285714,
						3,
						0
					],
					[
						77035.7142857143,
						2,
						0
					],
					[
						76178.5714285715,
						1,
						0
					],
					[
						76285.7142857143,
						2,
						0
					],
					[
						75428.5714285715,
						6,
						324,
						"brandy"
					]
				],
				"typeOfSection": 0,
				"gfSection": false,
				"altAnim": false,
				"mustHitSection": true,
				"changeBPM": false,
				"bpm": 125
			},
			{
				"sectionBeats": 4,
				"sectionNotes": [
					[
						77357.1428571429,
						1,
						0
					],
					[
						77464.2857142858,
						2,
						0
					],
					[
						77142.8571428572,
						0,
						0
					],
					[
						77571.4285714286,
						3,
						0
					],
					[
						77678.5714285715,
						0,
						0
					],
					[
						77250,
						0,
						0
					],
					[
						77785.7142857143,
						3,
						0
					],
					[
						77892.8571428572,
						2,
						0
					],
					[
						78000,
						1,
						0
					],
					[
						78107.1428571429,
						2,
						0
					],
					[
						78214.2857142858,
						1,
						0
					],
					[
						78321.4285714286,
						2,
						0
					],
					[
						78428.5714285715,
						3,
						0
					],
					[
						78535.7142857143,
						3,
						0
					],
					[
						78642.8571428572,
						0,
						0
					],
					[
						78750,
						2,
						0
					],
					[
						77142.8571428572,
						4,
						321.428571428571
					],
					[
						77571.4285714286,
						6,
						321.428571428571
					],
					[
						78000,
						5,
						321.428571428571
					],
					[
						78428.5714285715,
						6,
						0
					],
					[
						78428.5714285715,
						4,
						321.428571428571
					]
				],
				"typeOfSection": 0,
				"gfSection": false,
				"altAnim": false,
				"mustHitSection": true,
				"changeBPM": false,
				"bpm": 125
			},
			{
				"sectionBeats": 4,
				"sectionNotes": [
					[
						78857.1428571429,
						1,
						0
					],
					[
						79071.4285714286,
						1,
						0
					],
					[
						79178.5714285715,
						2,
						0
					],
					[
						79285.7142857143,
						0,
						0
					],
					[
						79500,
						2,
						0
					],
					[
						79714.2857142858,
						3,
						0
					],
					[
						79821.4285714286,
						2,
						0
					],
					[
						80035.7142857143,
						1,
						0
					],
					[
						80464.2857142858,
						1,
						0
					],
					[
						78857.1428571429,
						7,
						750
					],
					[
						79714.2857142857,
						4,
						750
					]
				],
				"typeOfSection": 0,
				"gfSection": false,
				"altAnim": false,
				"mustHitSection": true,
				"changeBPM": false,
				"bpm": 125
			},
			{
				"sectionBeats": 4,
				"sectionNotes": [
					[
						80571.4285714286,
						2,
						321.428571428571
					],
					[
						81321.4285714286,
						0,
						0
					],
					[
						81428.5714285715,
						1,
						321.428571428571
					],
					[
						81857.1428571429,
						3,
						321.428571428571
					],
					[
						80571.4285714286,
						5,
						750
					],
					[
						81428.5714285714,
						6,
						750
					]
				],
				"typeOfSection": 0,
				"gfSection": false,
				"altAnim": false,
				"mustHitSection": true,
				"changeBPM": false,
				"bpm": 125
			},
			{
				"sectionBeats": 4,
				"sectionNotes": [
					[
						82285.7142857143,
						6,
						321.428571428571
					],
					[
						82285.7142857143,
						0,
						750
					]
				],
				"typeOfSection": 0,
				"gfSection": false,
				"altAnim": false,
				"mustHitSection": false,
				"changeBPM": false,
				"bpm": 125
			},
			{
				"typeOfSection": 0,
				"sectionNotes": [
					[
						84857.1428571429,
						1,
						750
					],
					[
						84000,
						2,
						750
					]
				],
				"sectionBeats": 4,
				"altAnim": false,
				"gfSection": false,
				"bpm": 125,
				"changeBPM": false,
				"mustHitSection": false
			},
			{
				"typeOfSection": 0,
				"sectionNotes": [
					[
						85714.2857142857,
						0,
						750
					],
					[
						86571.4285714286,
						3,
						321.428571428571
					],
					[
						87000,
						0,
						321.428571428571
					]
				],
				"sectionBeats": 4,
				"altAnim": false,
				"gfSection": false,
				"bpm": 125,
				"changeBPM": false,
				"mustHitSection": false
			},
			{
				"sectionBeats": 4,
				"sectionNotes": [
					[
						88285.7142857143,
						1,
						750
					],
					[
						87428.5714285714,
						2,
						750
					]
				],
				"typeOfSection": 0,
				"gfSection": false,
				"altAnim": false,
				"mustHitSection": false,
				"changeBPM": false,
				"bpm": 125
			},
			{
				"sectionBeats": 4,
				"sectionNotes": [
					[
						89142.8571428571,
						3,
						321.428571428571
					],
					[
						89571.4285714286,
						1,
						107.142857142857
					],
					[
						89785.7142857143,
						3,
						107.142857142857
					],
					[
						90000,
						1,
						0
					],
					[
						90214.2857142857,
						1,
						0
					],
					[
						90321.4285714286,
						1,
						0
					],
					[
						90107.1428571429,
						0,
						0
					],
					[
						90428.5714285714,
						3,
						0
					],
					[
						90535.7142857143,
						1,
						0
					],
					[
						90642.8571428571,
						1,
						0
					],
					[
						90750,
						2,
						0
					]
				],
				"typeOfSection": 0,
				"gfSection": false,
				"altAnim": false,
				"mustHitSection": false,
				"changeBPM": false,
				"bpm": 180
			},
			{
				"typeOfSection": 0,
				"sectionNotes": [
					[
						90857.1428571429,
						0,
						0
					],
					[
						91714.2857142857,
						2,
						0
					],
					[
						90857.1428571429,
						1,
						321.428571428571
					],
					[
						91285.7142857143,
						3,
						321.428571428571
					],
					[
						91714.2857142857,
						0,
						321.428571428571
					],
					[
						92142.8571428571,
						2,
						0
					],
					[
						92142.8571428571,
						3,
						321.428571428571
					]
				],
				"sectionBeats": 4,
				"altAnim": false,
				"gfSection": false,
				"bpm": 180,
				"changeBPM": false,
				"mustHitSection": false
			},
			{
				"typeOfSection": 0,
				"sectionNotes": [
					[
						92571.4285714286,
						0,
						321.428571428571
					],
					[
						93000,
						1,
						107.142857142857
					],
					[
						93214.2857142857,
						3,
						107.142857142857
					],
					[
						93428.5714285714,
						1,
						321.428571428571
					],
					[
						93857.1428571429,
						0,
						321.428571428571
					]
				],
				"sectionBeats": 4,
				"altAnim": false,
				"gfSection": false,
				"bpm": 140,
				"changeBPM": false,
				"mustHitSection": false
			},
			{
				"typeOfSection": 0,
				"sectionNotes": [
					[
						95571.4285714286,
						1,
						0
					],
					[
						94285.7142857143,
						2,
						321.428571428571
					],
					[
						94714.2857142857,
						0,
						107.142857142857
					],
					[
						94928.5714285714,
						3,
						107.142857142857
					],
					[
						95142.8571428571,
						1,
						321.428571428571
					],
					[
						95571.4285714286,
						2,
						321.428571428571
					]
				],
				"sectionBeats": 4,
				"altAnim": false,
				"gfSection": false,
				"bpm": 140,
				"changeBPM": false,
				"mustHitSection": false
			},
			{
				"sectionBeats": 4,
				"sectionNotes": [
					[
						96000,
						0,
						750
					]
				],
				"typeOfSection": 0,
				"gfSection": false,
				"altAnim": false,
				"mustHitSection": true,
				"changeBPM": false,
				"bpm": 140
			},
			{
				"sectionBeats": 4,
				"sectionNotes": [
					[
						98571.4285714286,
						1,
						750
					],
					[
						97714.2857142857,
						2,
						750
					]
				],
				"typeOfSection": 0,
				"gfSection": false,
				"altAnim": false,
				"mustHitSection": true,
				"changeBPM": false,
				"bpm": 140
			},
			{
				"sectionBeats": 4,
				"sectionNotes": [
					[
						99428.5714285714,
						0,
						750
					],
					[
						100285.714285714,
						3,
						321.428571428571
					],
					[
						100714.285714286,
						0,
						321.428571428571
					]
				],
				"typeOfSection": 0,
				"gfSection": false,
				"altAnim": false,
				"mustHitSection": true,
				"changeBPM": false,
				"bpm": 140
			},
			{
				"sectionBeats": 4,
				"sectionNotes": [
					[
						102000,
						1,
						750
					],
					[
						101142.857142857,
						2,
						750
					]
				],
				"typeOfSection": 0,
				"gfSection": false,
				"altAnim": false,
				"mustHitSection": true,
				"changeBPM": false,
				"bpm": 140
			},
			{
				"sectionBeats": 4,
				"sectionNotes": [
					[
						102857.142857143,
						3,
						321.428571428571
					],
					[
						103285.714285714,
						1,
						107.142857142857
					],
					[
						103500,
						3,
						107.142857142857
					],
					[
						103714.285714286,
						1,
						0
					],
					[
						103928.571428571,
						1,
						0
					],
					[
						104035.714285714,
						1,
						0
					],
					[
						103821.428571429,
						0,
						0
					],
					[
						104142.857142857,
						3,
						0
					],
					[
						104250,
						1,
						0
					],
					[
						104357.142857143,
						1,
						0
					],
					[
						104464.285714286,
						2,
						0
					],
					[
						102857.142857143,
						4,
						321.428571428571
					],
					[
						103285.714285714,
						7,
						107.142857142857
					],
					[
						103500,
						5,
						107.142857142857
					],
					[
						103714.285714286,
						6,
						107.142857142857
					],
					[
						103928.571428571,
						4,
						535.714285714286
					]
				],
				"typeOfSection": 0,
				"gfSection": false,
				"altAnim": false,
				"mustHitSection": true,
				"changeBPM": false,
				"bpm": 140
			},
			{
				"typeOfSection": 0,
				"sectionNotes": [
					[
						104571.428571429,
						0,
						0
					],
					[
						105428.571428571,
						2,
						0
					],
					[
						104571.428571429,
						1,
						321.428571428571
					],
					[
						105000,
						3,
						321.428571428571
					],
					[
						105428.571428571,
						0,
						321.428571428571
					],
					[
						105857.142857143,
						2,
						0
					],
					[
						105857.142857143,
						3,
						321.428571428571
					],
					[
						104571.428571429,
						5,
						107.142857142857
					],
					[
						104785.714285714,
						4,
						107.142857142857
					],
					[
						105000,
						5,
						107.142857142857
					],
					[
						105214.285714286,
						7,
						107.142857142857
					],
					[
						105428.571428571,
						5,
						535.714285714286
					]
				],
				"sectionBeats": 4,
				"altAnim": false,
				"gfSection": false,
				"bpm": 140,
				"changeBPM": false,
				"mustHitSection": true
			},
			{
				"typeOfSection": 0,
				"sectionNotes": [
					[
						106285.714285714,
						0,
						321.428571428571
					],
					[
						106714.285714286,
						1,
						107.142857142857
					],
					[
						106928.571428571,
						3,
						107.142857142857
					],
					[
						107142.857142857,
						1,
						321.428571428571
					],
					[
						107571.428571429,
						0,
						321.428571428571
					],
					[
						106285.714285714,
						4,
						321.428571428571
					],
					[
						106714.285714286,
						7,
						107.142857142857
					],
					[
						106928.571428571,
						4,
						107.142857142857
					],
					[
						107142.857142857,
						7,
						214.285714285714
					],
					[
						107357.142857143,
						6,
						535.714285714286
					]
				],
				"sectionBeats": 4,
				"altAnim": false,
				"gfSection": false,
				"bpm": 140,
				"changeBPM": false,
				"mustHitSection": true
			},
			{
				"typeOfSection": 0,
				"sectionNotes": [
					[
						109285.714285714,
						1,
						0
					],
					[
						108000,
						2,
						321.428571428571
					],
					[
						108428.571428571,
						0,
						107.142857142857
					],
					[
						108642.857142857,
						3,
						107.142857142857
					],
					[
						108857.142857143,
						1,
						321.428571428571
					],
					[
						109285.714285714,
						2,
						321.428571428571
					],
					[
						108000,
						5,
						107.142857142857
					],
					[
						108214.285714286,
						4,
						107.142857142857
					],
					[
						108428.571428571,
						5,
						107.142857142857
					],
					[
						108642.857142857,
						7,
						107.142857142857
					],
					[
						108857.142857143,
						6,
						535.714285714286
					]
				],
				"sectionBeats": 4,
				"altAnim": false,
				"gfSection": false,
				"bpm": 140,
				"changeBPM": false,
				"mustHitSection": true
			},
			{
				"typeOfSection": 0,
				"sectionNotes": [
					[
						110571.428571429,
						1,
						0
					],
					[
						109714.285714286,
						3,
						107.142857142857
					],
					[
						109928.571428571,
						1,
						107.142857142857
					],
					[
						110142.857142857,
						0,
						107.142857142857
					],
					[
						110357.142857143,
						3,
						107.142857142857
					],
					[
						111000,
						0,
						107.142857142857
					],
					[
						111214.285714286,
						1,
						107.142857142857
					]
				],
				"sectionBeats": 4,
				"altAnim": false,
				"gfSection": false,
				"bpm": 140,
				"changeBPM": false,
				"mustHitSection": false
			},
			{
				"typeOfSection": 0,
				"sectionNotes": [
					[
						111428.571428571,
						3,
						0
					],
					[
						111535.714285714,
						0,
						0
					],
					[
						111642.857142857,
						1,
						0
					],
					[
						111857.142857143,
						1,
						0
					],
					[
						111964.285714286,
						0,
						0
					],
					[
						112071.428571429,
						2,
						0
					],
					[
						111750,
						3,
						0
					],
					[
						112178.571428571,
						1,
						0
					],
					[
						112285.714285714,
						3,
						0
					],
					[
						112392.857142857,
						0,
						0
					],
					[
						112500,
						1,
						0
					],
					[
						112607.142857143,
						3,
						0
					],
					[
						112714.285714286,
						1,
						0
					],
					[
						112821.428571429,
						0,
						0
					],
					[
						112928.571428571,
						2,
						0
					],
					[
						113035.714285714,
						1,
						0
					]
				],
				"sectionBeats": 4,
				"altAnim": false,
				"gfSection": false,
				"bpm": 140,
				"changeBPM": false,
				"mustHitSection": false
			},
			{
				"typeOfSection": 0,
				"sectionNotes": [
					[
						113142.857142857,
						3,
						321.428571428571
					],
					[
						113785.714285714,
						2,
						321.428571428571
					],
					[
						114428.571428571,
						0,
						321.428571428571
					]
				],
				"sectionBeats": 4,
				"altAnim": false,
				"gfSection": false,
				"bpm": 140,
				"changeBPM": false,
				"mustHitSection": false
			},
			{
				"typeOfSection": 0,
				"sectionNotes": [
					[
						114857.142857143,
						3,
						321.428571428571
					],
					[
						115285.714285714,
						1,
						321.428571428571
					],
					[
						115714.285714286,
						2,
						321.428571428571
					],
					[
						116142.857142857,
						1,
						321.428571428571
					]
				],
				"sectionBeats": 4,
				"altAnim": false,
				"gfSection": false,
				"bpm": 140,
				"changeBPM": false,
				"mustHitSection": false
			},
			{
				"typeOfSection": 0,
				"sectionNotes": [
					[
						117000,
						1,
						107.142857142857
					],
					[
						117214.285714286,
						3,
						107.142857142857
					],
					[
						117428.571428571,
						1,
						107.142857142857
					],
					[
						117642.857142857,
						2,
						535.714285714286
					],
					[
						116571.428571429,
						4,
						321.428571428571,
						"brandy"
					]
				],
				"sectionBeats": 4,
				"altAnim": false,
				"gfSection": false,
				"bpm": 140,
				"changeBPM": false,
				"mustHitSection": true
			},
			{
				"typeOfSection": 0,
				"sectionNotes": [
					[
						118285.714285714,
						1,
						107.142857142857
					],
					[
						118500,
						2,
						107.142857142857
					],
					[
						118714.285714286,
						1,
						107.142857142857
					],
					[
						118928.571428571,
						2,
						107.142857142857
					],
					[
						119142.857142857,
						3,
						750
					],
					[
						119142.857142857,
						2,
						0
					],
					[
						118285.714285714,
						6,
						321.428571428571,
						"brandy"
					],
					[
						119142.857142857,
						6,
						321.428571428571,
						"brandy"
					]
				],
				"sectionBeats": 4,
				"altAnim": false,
				"gfSection": false,
				"bpm": 140,
				"changeBPM": false,
				"mustHitSection": true
			},
			{
				"typeOfSection": 0,
				"sectionNotes": [
					[
						120428.571428571,
						2,
						0
					],
					[
						120000,
						0,
						321.428571428571
					],
					[
						120428.571428571,
						3,
						107.142857142857
					],
					[
						120642.857142857,
						1,
						107.142857142857
					],
					[
						120857.142857143,
						3,
						214.285714285714
					],
					[
						121178.571428571,
						2,
						428.571428571428
					],
					[
						120000,
						7,
						1607.14285714286,
						"brandy"
					]
				],
				"sectionBeats": 4,
				"altAnim": false,
				"gfSection": false,
				"bpm": 140,
				"changeBPM": false,
				"mustHitSection": true
			},
			{
				"typeOfSection": 0,
				"sectionNotes": [
					[
						121714.285714286,
						1,
						107.142857142857
					],
					[
						121928.571428571,
						2,
						107.142857142857
					],
					[
						122142.857142857,
						1,
						107.142857142857
					],
					[
						122357.142857143,
						2,
						107.142857142857
					],
					[
						122571.428571428,
						0,
						535.714285714286
					]
				],
				"sectionBeats": 4,
				"altAnim": false,
				"gfSection": false,
				"bpm": 140,
				"changeBPM": false,
				"mustHitSection": true
			},
			{
				"typeOfSection": 0,
				"sectionNotes": [
					[
						124285.714285714,
						1,
						0
					],
					[
						123428.571428571,
						3,
						107.142857142857
					],
					[
						123642.857142857,
						1,
						107.142857142857
					],
					[
						123857.142857143,
						0,
						107.142857142857
					],
					[
						124071.428571429,
						3,
						107.142857142857
					],
					[
						124714.285714286,
						0,
						107.142857142857
					],
					[
						124928.571428571,
						1,
						107.142857142857
					],
					[
						123428.571428571,
						6,
						1607.14285714286,
						"brandy"
					]
				],
				"sectionBeats": 4,
				"altAnim": false,
				"gfSection": false,
				"bpm": 140,
				"changeBPM": false,
				"mustHitSection": true
			},
			{
				"typeOfSection": 0,
				"sectionNotes": [
					[
						125142.857142857,
						3,
						0
					],
					[
						125250,
						0,
						0
					],
					[
						125357.142857143,
						1,
						0
					],
					[
						125571.428571429,
						1,
						0
					],
					[
						125678.571428571,
						0,
						0
					],
					[
						125785.714285714,
						2,
						0
					],
					[
						125464.285714286,
						3,
						0
					],
					[
						125892.857142857,
						1,
						0
					],
					[
						126000,
						3,
						0
					],
					[
						126107.142857143,
						0,
						0
					],
					[
						126214.285714286,
						1,
						0
					],
					[
						126321.428571429,
						3,
						0
					],
					[
						126428.571428571,
						1,
						0
					],
					[
						126535.714285714,
						0,
						0
					],
					[
						126642.857142857,
						2,
						0
					],
					[
						126750,
						1,
						0
					]
				],
				"sectionBeats": 4,
				"altAnim": false,
				"gfSection": false,
				"bpm": 140,
				"changeBPM": false,
				"mustHitSection": true
			},
			{
				"typeOfSection": 0,
				"sectionNotes": [
					[
						126857.142857143,
						3,
						321.428571428571
					],
					[
						127500,
						2,
						321.428571428571
					],
					[
						128142.857142857,
						0,
						321.428571428571
					],
					[
						126857.142857143,
						4,
						1607.14285714286,
						"brandy"
					]
				],
				"sectionBeats": 4,
				"altAnim": false,
				"gfSection": false,
				"bpm": 140,
				"changeBPM": false,
				"mustHitSection": true
			},
			{
				"typeOfSection": 0,
				"sectionNotes": [
					[
						128571.428571429,
						3,
						321.428571428571
					],
					[
						129000,
						1,
						321.428571428571
					],
					[
						129428.571428571,
						2,
						321.428571428571
					],
					[
						129857.142857143,
						1,
						321.428571428571
					],
					[
						128571.428571428,
						5,
						1607.14285714286,
						"brandy"
					]
				],
				"sectionBeats": 4,
				"altAnim": false,
				"gfSection": false,
				"bpm": 140,
				"changeBPM": false,
				"mustHitSection": true
			},
			{
				"typeOfSection": 0,
				"sectionNotes": [
					[
						130285.714285714,
						1,
						108,
						"brandy"
					],
					[
						130500,
						2,
						108,
						"brandy"
					],
					[
						130714.285714286,
						3,
						0,
						"brandy"
					],
					[
						130821.428571428,
						0,
						0,
						"brandy"
					],
					[
						130928.571428571,
						2,
						0,
						"brandy"
					],
					[
						131035.714285714,
						3,
						0,
						"brandy"
					],
					[
						131142.857142857,
						1,
						0,
						"brandy"
					],
					[
						131357.142857143,
						2,
						0,
						"brandy"
					],
					[
						131464.285714286,
						1,
						0,
						"brandy"
					],
					[
						131571.428571428,
						2,
						0,
						"brandy"
					],
					[
						131785.714285714,
						2,
						0,
						"brandy"
					],
					[
						131892.857142857,
						0,
						0,
						"brandy"
					]
				],
				"sectionBeats": 4,
				"altAnim": false,
				"gfSection": false,
				"bpm": 140,
				"changeBPM": false,
				"mustHitSection": false
			},
			{
				"typeOfSection": 0,
				"sectionNotes": [
					[
						132000,
						2,
						0,
						"brandy"
					],
					[
						132107.142857143,
						0,
						0,
						"brandy"
					],
					[
						132214.285714286,
						2,
						0,
						"brandy"
					],
					[
						132321.428571428,
						3,
						0,
						"brandy"
					],
					[
						132428.571428571,
						2,
						0,
						"brandy"
					],
					[
						132642.857142857,
						0,
						0,
						"brandy"
					],
					[
						132785.714285714,
						0,
						0,
						"brandy"
					],
					[
						132857.142857143,
						2,
						0,
						"brandy"
					],
					[
						132964.285714286,
						2,
						0,
						"brandy"
					],
					[
						133071.428571428,
						0,
						0,
						"brandy"
					],
					[
						133178.571428571,
						1,
						0,
						"brandy"
					],
					[
						133285.714285714,
						2,
						0,
						"brandy"
					],
					[
						133392.857142857,
						1,
						0,
						"brandy"
					],
					[
						133500,
						0,
						0,
						"brandy"
					],
					[
						133607.142857143,
						0,
						0,
						"brandy"
					]
				],
				"sectionBeats": 4,
				"altAnim": false,
				"gfSection": false,
				"bpm": 140,
				"changeBPM": false,
				"mustHitSection": false
			},
			{
				"typeOfSection": 0,
				"sectionNotes": [
					[
						133714.285714286,
						3,
						0,
						"brandy"
					],
					[
						133821.428571428,
						3,
						0,
						"brandy"
					],
					[
						133928.571428571,
						2,
						0,
						"brandy"
					],
					[
						134035.714285714,
						2,
						0,
						"brandy"
					],
					[
						134142.857142857,
						0,
						0,
						"brandy"
					],
					[
						134250,
						2,
						216,
						"brandy"
					],
					[
						133982.142857143,
						0,
						0,
						"brandy"
					],
					[
						134089.285714286,
						1,
						0,
						"brandy"
					],
					[
						134571.428571428,
						0,
						324,
						"brandy"
					],
					[
						135000,
						2,
						108,
						"brandy"
					],
					[
						135214.285714286,
						1,
						108,
						"brandy"
					]
				],
				"sectionBeats": 4,
				"altAnim": false,
				"gfSection": false,
				"bpm": 140,
				"changeBPM": false,
				"mustHitSection": false
			},
			{
				"typeOfSection": 0,
				"sectionNotes": [
					[
						135428.571428571,
						3,
						324,
						"brandy"
					],
					[
						136285.714285714,
						0,
						108,
						"brandy"
					],
					[
						136500,
						1,
						540,
						"brandy"
					]
				],
				"sectionBeats": 4,
				"altAnim": false,
				"gfSection": false,
				"bpm": 140,
				"changeBPM": false,
				"mustHitSection": false
			},
			{
				"typeOfSection": 0,
				"sectionNotes": [
					[
						137142.857142857,
						1,
						107.142857142857
					],
					[
						137357.142857143,
						2,
						107.142857142857
					],
					[
						137678.571428571,
						0,
						0
					],
					[
						137785.714285714,
						2,
						0
					],
					[
						137892.857142857,
						3,
						0
					],
					[
						138000,
						1,
						0
					],
					[
						138321.428571428,
						1,
						0
					],
					[
						138214.285714286,
						2,
						0
					],
					[
						138428.571428571,
						2,
						0
					],
					[
						138642.857142857,
						2,
						0
					],
					[
						138750,
						0,
						0
					],
					[
						137571.428571428,
						3,
						0
					]
				],
				"sectionBeats": 4,
				"altAnim": false,
				"gfSection": false,
				"bpm": 140,
				"changeBPM": false,
				"mustHitSection": true
			},
			{
				"typeOfSection": 0,
				"sectionNotes": [
					[
						138857.142857143,
						2,
						0
					],
					[
						138964.285714286,
						0,
						0
					],
					[
						139071.428571428,
						2,
						0
					],
					[
						139178.571428571,
						3,
						0
					],
					[
						139285.714285714,
						2,
						0
					],
					[
						139500,
						0,
						0
					],
					[
						139714.285714286,
						2,
						0
					],
					[
						139767.857142857,
						0,
						0
					],
					[
						139928.571428571,
						0,
						0
					],
					[
						139821.428571428,
						2,
						0
					],
					[
						140035.714285714,
						1,
						0
					],
					[
						140142.857142857,
						2,
						0
					],
					[
						140250,
						1,
						0
					],
					[
						140357.142857143,
						0,
						0
					],
					[
						140464.285714286,
						0,
						0
					]
				],
				"sectionBeats": 4,
				"altAnim": false,
				"gfSection": false,
				"bpm": 140,
				"changeBPM": false,
				"mustHitSection": true
			},
			{
				"typeOfSection": 0,
				"sectionNotes": [
					[
						140571.428571428,
						3,
						0
					],
					[
						140678.571428571,
						3,
						0
					],
					[
						140785.714285714,
						2,
						0
					],
					[
						140892.857142857,
						2,
						0
					],
					[
						140839.285714286,
						0,
						0
					],
					[
						141000,
						0,
						0
					],
					[
						141107.142857143,
						2,
						214.285714285714
					],
					[
						141428.571428571,
						0,
						321.428571428571
					],
					[
						141857.142857143,
						2,
						107.142857142857
					],
					[
						142071.428571428,
						1,
						107.142857142857
					],
					[
						140946.428571428,
						1,
						0
					]
				],
				"sectionBeats": 4,
				"altAnim": false,
				"gfSection": false,
				"bpm": 140,
				"changeBPM": false,
				"mustHitSection": true
			},
			{
				"typeOfSection": 0,
				"sectionNotes": [
					[
						142285.714285714,
						3,
						321.428571428571
					],
					[
						143142.857142857,
						0,
						107.142857142857
					],
					[
						143357.142857143,
						1,
						535.714285714286
					]
				],
				"sectionBeats": 4,
				"altAnim": false,
				"gfSection": false,
				"bpm": 140,
				"changeBPM": false,
				"mustHitSection": true
			},
			{
				"typeOfSection": 0,
				"sectionNotes": [
					[
						144000,
						0,
						540,
						"brandy"
					],
					[
						144642.857142857,
						1,
						0,
						"brandy"
					],
					[
						144750,
						2,
						0,
						"brandy"
					],
					[
						144857.142857143,
						3,
						540,
						"brandy"
					],
					[
						145500,
						1,
						540,
						"brandy"
					]
				],
				"sectionBeats": 4,
				"altAnim": false,
				"gfSection": false,
				"bpm": 140,
				"changeBPM": false,
				"mustHitSection": false
			},
			{
				"typeOfSection": 0,
				"sectionNotes": [
					[
						146142.857142857,
						0,
						540,
						"brandy"
					],
					[
						146785.714285714,
						3,
						540,
						"brandy"
					]
				],
				"sectionBeats": 4,
				"altAnim": false,
				"gfSection": false,
				"bpm": 140,
				"changeBPM": false,
				"mustHitSection": false
			},
			{
				"typeOfSection": 0,
				"sectionNotes": [
					[
						147428.571428571,
						2,
						540,
						"brandy"
					],
					[
						148071.428571428,
						1,
						540,
						"brandy"
					],
					[
						148714.285714286,
						0,
						324,
						"brandy"
					]
				],
				"sectionBeats": 4,
				"altAnim": false,
				"gfSection": false,
				"bpm": 140,
				"changeBPM": false,
				"mustHitSection": false
			},
			{
				"typeOfSection": 0,
				"sectionNotes": [
					[
						149142.857142857,
						1,
						540,
						"brandy"
					],
					[
						149785.714285714,
						0,
						0,
						"brandy"
					],
					[
						149892.857142857,
						1,
						0,
						"brandy"
					],
					[
						150000,
						3,
						324,
						"brandy"
					],
					[
						150428.571428571,
						2,
						324,
						"brandy"
					]
				],
				"sectionBeats": 4,
				"altAnim": false,
				"gfSection": false,
				"bpm": 140,
				"changeBPM": false,
				"mustHitSection": false
			},
			{
				"typeOfSection": 0,
				"sectionNotes": [
					[
						150857.142857143,
						0,
						535.714285714286
					],
					[
						151500,
						1,
						0
					],
					[
						151607.142857143,
						2,
						0
					],
					[
						151714.285714286,
						3,
						535.714285714286
					],
					[
						152357.142857143,
						1,
						535.714285714286
					],
					[
						150857.142857143,
						7,
						756,
						"brandy"
					]
				],
				"sectionBeats": 4,
				"altAnim": false,
				"gfSection": false,
				"bpm": 140,
				"changeBPM": false,
				"mustHitSection": true
			},
			{
				"typeOfSection": 0,
				"sectionNotes": [
					[
						153000,
						0,
						535.714285714286
					],
					[
						153642.857142857,
						3,
						535.714285714286
					]
				],
				"sectionBeats": 4,
				"altAnim": false,
				"gfSection": false,
				"bpm": 140,
				"changeBPM": false,
				"mustHitSection": true
			},
			{
				"typeOfSection": 0,
				"sectionNotes": [
					[
						154285.714285714,
						2,
						535.714285714286
					],
					[
						154928.571428571,
						1,
						535.714285714286
					],
					[
						155571.428571428,
						0,
						321.428571428571
					]
				],
				"sectionBeats": 4,
				"altAnim": false,
				"gfSection": false,
				"bpm": 140,
				"changeBPM": false,
				"mustHitSection": true
			},
			{
				"typeOfSection": 0,
				"sectionNotes": [
					[
						156000,
						1,
						535.714285714286
					],
					[
						156750,
						1,
						0
					],
					[
						156642.857142857,
						0,
						0
					],
					[
						156857.142857143,
						3,
						750
					]
				],
				"sectionBeats": 4,
				"altAnim": false,
				"gfSection": false,
				"bpm": 140,
				"changeBPM": false,
				"mustHitSection": true
			},
			{
				"typeOfSection": 0,
				"sectionNotes": [
					[
						158142.857142857,
						6,
						107.142857142857
					],
					[
						158357.142857143,
						5,
						107.142857142857
					],
					[
						158785.714285714,
						7,
						107.142857142857
					],
					[
						159000,
						5,
						107.142857142857
					],
					[
						159214.285714286,
						4,
						107.142857142857
					],
					[
						157714.285714286,
						0,
						107.142857142857
					],
					[
						157714.285714286,
						4,
						107.142857142857
					],
					[
						158142.857142857,
						2,
						107.142857142857
					],
					[
						158357.142857143,
						3,
						107.142857142857
					],
					[
						158785.714285714,
						2,
						107.142857142857
					],
					[
						159214.285714286,
						2,
						107.142857142857
					],
					[
						159000,
						0,
						107.142857142857
					]
				],
				"sectionBeats": 4,
				"altAnim": false,
				"gfSection": false,
				"bpm": 140,
				"changeBPM": false,
				"mustHitSection": false
			},
			{
				"typeOfSection": 0,
				"sectionNotes": [
					[
						159428.571428571,
						4,
						107.142857142857
					],
					[
						159857.142857143,
						1,
						107.142857142857
					],
					[
						160285.714285714,
						1,
						107.142857142857
					],
					[
						160071.428571428,
						0,
						107.142857142857
					],
					[
						159428.571428571,
						3,
						107.142857142857
					],
					[
						160714.285714286,
						2,
						107.142857142857
					],
					[
						160928.571428571,
						3,
						107.142857142857
					],
					[
						159857.142857143,
						5,
						107.142857142857
					],
					[
						160071.428571428,
						6,
						107.142857142857
					],
					[
						160285.714285714,
						5,
						107.142857142857
					],
					[
						160714.285714286,
						4,
						107.142857142857
					],
					[
						160928.571428571,
						5,
						107.142857142857
					]
				],
				"sectionBeats": 4,
				"altAnim": false,
				"gfSection": false,
				"bpm": 140,
				"changeBPM": false,
				"mustHitSection": true
			},
			{
				"typeOfSection": 0,
				"sectionNotes": [
					[
						161142.857142857,
						1,
						321.428571428571
					],
					[
						161142.857142857,
						5,
						321.428571428571
					],
					[
						162000,
						5,
						321.428571428571
					],
					[
						162428.571428571,
						7,
						321.428571428571
					],
					[
						162000,
						2,
						321.428571428571
					],
					[
						162428.571428571,
						1,
						321.428571428571
					]
				],
				"sectionBeats": 4,
				"altAnim": false,
				"gfSection": false,
				"bpm": 140,
				"changeBPM": false,
				"mustHitSection": false
			},
			{
				"typeOfSection": 0,
				"sectionNotes": [
					[
						162857.142857143,
						1,
						321.428571428571
					],
					[
						162857.142857143,
						7,
						321.428571428571
					],
					[
						163714.285714286,
						1,
						321.428571428571
					],
					[
						163714.285714286,
						5,
						321.428571428571
					],
					[
						164142.857142857,
						7,
						321.428571428571
					],
					[
						164142.857142857,
						0,
						321.428571428571
					]
				],
				"sectionBeats": 4,
				"altAnim": false,
				"gfSection": false,
				"bpm": 140,
				"changeBPM": false,
				"mustHitSection": true
			},
			{
				"typeOfSection": 0,
				"sectionNotes": [
					[
						164571.428571428,
						2,
						1607.14285714286
					]
				],
				"sectionBeats": 4,
				"altAnim": false,
				"gfSection": false,
				"bpm": 140,
				"changeBPM": false,
				"mustHitSection": false
			},
			{
				"typeOfSection": 0,
				"sectionNotes": [
					[
						166285.714285714,
						1,
						750
					],
					[
						167142.857142857,
						0,
						750
					]
				],
				"sectionBeats": 4,
				"altAnim": false,
				"gfSection": false,
				"bpm": 140,
				"changeBPM": false,
				"mustHitSection": false
			},
			{
				"typeOfSection": 0,
				"sectionNotes": [
					[
						168000,
						2,
						1607.14285714286
					]
				],
				"sectionBeats": 4,
				"altAnim": false,
				"gfSection": false,
				"bpm": 140,
				"changeBPM": false,
				"mustHitSection": false
			},
			{
				"typeOfSection": 0,
				"sectionNotes": [
					[
						169714.285714286,
						1,
						750
					],
					[
						170571.428571428,
						0,
						750
					]
				],
				"sectionBeats": 4,
				"altAnim": false,
				"gfSection": false,
				"bpm": 140,
				"changeBPM": false,
				"mustHitSection": false
			},
			{
				"typeOfSection": 0,
				"sectionNotes": [
					[
						171428.571428571,
						3,
						750
					],
					[
						172285.714285714,
						0,
						321.428571428571
					],
					[
						172714.285714286,
						1,
						321.428571428571
					]
				],
				"sectionBeats": 4,
				"altAnim": false,
				"gfSection": false,
				"bpm": 140,
				"changeBPM": false,
				"mustHitSection": false
			},
			{
				"typeOfSection": 0,
				"sectionNotes": [
					[
						173142.857142857,
						2,
						750
					],
					[
						174428.571428571,
						1,
						321.428571428571
					],
					[
						174000,
						3,
						321.428571428571
					]
				],
				"sectionBeats": 4,
				"altAnim": false,
				"gfSection": false,
				"bpm": 140,
				"changeBPM": false,
				"mustHitSection": false
			},
			{
				"typeOfSection": 0,
				"sectionNotes": [
					[
						174857.142857143,
						0,
						750
					],
					[
						175714.285714286,
						1,
						750
					]
				],
				"sectionBeats": 4,
				"altAnim": false,
				"gfSection": false,
				"bpm": 140,
				"changeBPM": false,
				"mustHitSection": false
			},
			{
				"typeOfSection": 0,
				"sectionNotes": [
					[
						176571.428571428,
						3,
						750
					],
					[
						177428.571428571,
						0,
						750
					]
				],
				"sectionBeats": 4,
				"altAnim": false,
				"gfSection": false,
				"bpm": 140,
				"changeBPM": false,
				"mustHitSection": false
			},
			{
				"typeOfSection": 0,
				"sectionNotes": [
					[
						178285.714285714,
						2,
						1607.14285714286
					]
				],
				"sectionBeats": 4,
				"altAnim": false,
				"gfSection": false,
				"bpm": 140,
				"changeBPM": false,
				"mustHitSection": true
			},
			{
				"typeOfSection": 0,
				"sectionNotes": [
					[
						180000,
						1,
						750
					],
					[
						180857.142857143,
						0,
						750
					]
				],
				"sectionBeats": 4,
				"altAnim": false,
				"gfSection": false,
				"bpm": 140,
				"changeBPM": false,
				"mustHitSection": true
			},
			{
				"typeOfSection": 0,
				"sectionNotes": [
					[
						181714.285714286,
						2,
						1607.14285714286
					]
				],
				"sectionBeats": 4,
				"altAnim": false,
				"gfSection": false,
				"bpm": 140,
				"changeBPM": false,
				"mustHitSection": true
			},
			{
				"typeOfSection": 0,
				"sectionNotes": [
					[
						183428.571428571,
						1,
						750
					],
					[
						184285.714285714,
						0,
						750
					]
				],
				"sectionBeats": 4,
				"altAnim": false,
				"gfSection": false,
				"bpm": 140,
				"changeBPM": false,
				"mustHitSection": true
			},
			{
				"typeOfSection": 0,
				"sectionNotes": [
					[
						185142.857142857,
						3,
						750
					],
					[
						186000,
						0,
						321.428571428571
					],
					[
						186428.571428571,
						1,
						321.428571428571
					],
					[
						185142.857142857,
						4,
						750
					]
				],
				"sectionBeats": 4,
				"altAnim": false,
				"gfSection": false,
				"bpm": 140,
				"changeBPM": false,
				"mustHitSection": true
			},
			{
				"typeOfSection": 0,
				"sectionNotes": [
					[
						186857.142857143,
						2,
						750
					],
					[
						188142.857142857,
						1,
						321.428571428571
					],
					[
						187714.285714286,
						3,
						321.428571428571
					],
					[
						186857.142857143,
						5,
						750
					]
				],
				"sectionBeats": 4,
				"altAnim": false,
				"gfSection": false,
				"bpm": 140,
				"changeBPM": false,
				"mustHitSection": true
			},
			{
				"typeOfSection": 0,
				"sectionNotes": [
					[
						188571.428571428,
						0,
						750
					],
					[
						189428.571428571,
						1,
						750
					],
					[
						188571.428571428,
						6,
						750
					]
				],
				"sectionBeats": 4,
				"altAnim": false,
				"gfSection": false,
				"bpm": 140,
				"changeBPM": false,
				"mustHitSection": true
			},
			{
				"typeOfSection": 0,
				"sectionNotes": [
					[
						190285.714285714,
						3,
						750
					],
					[
						190285.714285714,
						4,
						750
					],
					[
						191142.857142857,
						7,
						750
					],
					[
						191142.857142857,
						1,
						750
					]
				],
				"sectionBeats": 4,
				"altAnim": false,
				"gfSection": false,
				"bpm": 140,
				"changeBPM": false,
				"mustHitSection": true
			},
			{
				"typeOfSection": 0,
				"sectionNotes": [
					[
						192000,
						4,
						1607.14285714286
					],
					[
						192000,
						0,
						107.142857142857
					],
					[
						192214.285714285,
						1,
						107.142857142857
					],
					[
						192428.571428571,
						2,
						107.142857142857
					],
					[
						192642.857142857,
						1,
						964.285714285714
					]
				],
				"sectionBeats": 4,
				"altAnim": false,
				"gfSection": false,
				"bpm": 140,
				"changeBPM": false,
				"mustHitSection": true
			},
			{
				"typeOfSection": 0,
				"sectionNotes": [],
				"sectionBeats": 4,
				"altAnim": false,
				"gfSection": false,
				"bpm": 140,
				"changeBPM": false,
				"mustHitSection": false
			},
			{
				"typeOfSection": 0,
				"sectionNotes": [],
				"sectionBeats": 4,
				"altAnim": false,
				"gfSection": false,
				"bpm": 140,
				"changeBPM": false,
				"mustHitSection": true
			},
			{
				"typeOfSection": 0,
				"sectionNotes": [],
				"sectionBeats": 4,
				"altAnim": false,
				"gfSection": false,
				"bpm": 140,
				"changeBPM": false,
				"mustHitSection": false
			},
			{
				"typeOfSection": 0,
				"sectionNotes": [],
				"sectionBeats": 4,
				"altAnim": false,
				"gfSection": false,
				"bpm": 140,
				"changeBPM": false,
				"mustHitSection": true
			},
			{
				"typeOfSection": 0,
				"sectionNotes": [],
				"sectionBeats": 4,
				"altAnim": false,
				"gfSection": false,
				"bpm": 140,
				"changeBPM": false,
				"mustHitSection": true
			},
			{
				"typeOfSection": 0,
				"sectionNotes": [],
				"sectionBeats": 4,
				"altAnim": false,
				"gfSection": false,
				"bpm": 140,
				"changeBPM": false,
				"mustHitSection": true
			}
		],
		"events": [],
		"player2": "steven",
		"splashSkin": "noteSplashes",
		"song": "Subdive",
		"needsVoices": true,
		"arrowSkin": "",
		"stage": "ocean",
		"validScore": true,
		"bpm": 140,
		"speed": 3
	}
}