<?xml version='1.0' encoding='utf-8'?>
<TextureAtlas imagePath="lynb-dialogue.png">
<SubTexture name="lynb-dialogue normal0000" x="0" y="0" width="406" height="691" frameX="-149" frameY="-46" frameWidth="671" frameHeight="743" />
<SubTexture name="lynb-dialogue normal0001" x="406" y="0" width="406" height="691" frameX="-149" frameY="-46" frameWidth="671" frameHeight="743" />
<SubTexture name="lynb-dialogue normal0002" x="406" y="0" width="406" height="691" frameX="-149" frameY="-46" frameWidth="671" frameHeight="743" />
<SubTexture name="lynb-dialogue normal0003" x="406" y="0" width="406" height="691" frameX="-149" frameY="-46" frameWidth="671" frameHeight="743" />
<SubTexture name="lynb-dialogue normal0004" x="406" y="0" width="406" height="691" frameX="-149" frameY="-46" frameWidth="671" frameHeight="743" />
<SubTexture name="lynb-dialogue happy0000" x="812" y="0" width="406" height="691" frameX="-149" frameY="-46" frameWidth="671" frameHeight="743" />
<SubTexture name="lynb-dialogue happy0001" x="1218" y="0" width="406" height="691" frameX="-149" frameY="-46" frameWidth="671" frameHeight="743" />
<SubTexture name="lynb-dialogue happy0002" x="1218" y="0" width="406" height="691" frameX="-149" frameY="-46" frameWidth="671" frameHeight="743" />
<SubTexture name="lynb-dialogue happy0003" x="1218" y="0" width="406" height="691" frameX="-149" frameY="-46" frameWidth="671" frameHeight="743" />
<SubTexture name="lynb-dialogue happy0004" x="1218" y="0" width="406" height="691" frameX="-149" frameY="-46" frameWidth="671" frameHeight="743" />
<SubTexture name="lynb-dialogue nervous0000" x="0" y="691" width="406" height="691" frameX="-149" frameY="-46" frameWidth="671" frameHeight="743" />
<SubTexture name="lynb-dialogue nervous0001" x="406" y="691" width="406" height="691" frameX="-149" frameY="-46" frameWidth="671" frameHeight="743" />
<SubTexture name="lynb-dialogue nervous0002" x="406" y="691" width="406" height="691" frameX="-149" frameY="-46" frameWidth="671" frameHeight="743" />
<SubTexture name="lynb-dialogue nervous0003" x="406" y="691" width="406" height="691" frameX="-149" frameY="-46" frameWidth="671" frameHeight="743" />
<SubTexture name="lynb-dialogue nervous0004" x="406" y="691" width="406" height="691" frameX="-149" frameY="-46" frameWidth="671" frameHeight="743" />
<SubTexture name="lynb-dialogue shock0000" x="812" y="691" width="406" height="691" frameX="-149" frameY="-46" frameWidth="671" frameHeight="743" />
<SubTexture name="lynb-dialogue shock0001" x="1218" y="691" width="406" height="691" frameX="-149" frameY="-46" frameWidth="671" frameHeight="743" />
<SubTexture name="lynb-dialogue shock0002" x="1218" y="691" width="406" height="691" frameX="-149" frameY="-46" frameWidth="671" frameHeight="743" />
<SubTexture name="lynb-dialogue shock0003" x="1218" y="691" width="406" height="691" frameX="-149" frameY="-46" frameWidth="671" frameHeight="743" />
<SubTexture name="lynb-dialogue shock0004" x="1218" y="691" width="406" height="691" frameX="-149" frameY="-46" frameWidth="671" frameHeight="743" />
<SubTexture name="lynb-dialogue mad0000" x="1624" y="0" width="406" height="691" frameX="-149" frameY="-46" frameWidth="671" frameHeight="743" />
<SubTexture name="lynb-dialogue mad0001" x="1624" y="691" width="406" height="691" frameX="-149" frameY="-46" frameWidth="671" frameHeight="743" />
<SubTexture name="lynb-dialogue mad0002" x="1624" y="691" width="406" height="691" frameX="-149" frameY="-46" frameWidth="671" frameHeight="743" />
<SubTexture name="lynb-dialogue mad0003" x="1624" y="691" width="406" height="691" frameX="-149" frameY="-46" frameWidth="671" frameHeight="743" />
<SubTexture name="lynb-dialogue mad0004" x="1624" y="691" width="406" height="691" frameX="-149" frameY="-46" frameWidth="671" frameHeight="743" />
</TextureAtlas>
